setup.py
mytest20170226/__init__.py
mytest20170226/hello.py
mytest20170226.egg-info/PKG-INFO
mytest20170226.egg-info/SOURCES.txt
mytest20170226.egg-info/dependency_links.txt
mytest20170226.egg-info/entry_points.txt
mytest20170226.egg-info/requires.txt
mytest20170226.egg-info/top_level.txt
mytest20170226.egg-info/zip-safe